cirtusai/__init__.py
cirtusai/agent.py
cirtusai/agents.py
cirtusai/auth.py
cirtusai/bridge.py
cirtusai/child_assets.py
cirtusai/child_services.py
cirtusai/cli.py
cirtusai/client.py
cirtusai/email.py
cirtusai/executor.py
cirtusai/governance.py
cirtusai/identity.py
cirtusai/marketplace.py
cirtusai/nfts.py
cirtusai/reputation.py
cirtusai/schemas.py
cirtusai/security.py
cirtusai/swap.py
cirtusai/wallets.py
cirtusai/async_/__init__.py
cirtusai/async_/agents.py
cirtusai/async_/auth.py
cirtusai/async_/client.py
cirtusai/async_/identity.py
cirtusai/async_/wallets.py
cirtusai_sdk-0.2.2.dist-info/METADATA
cirtusai_sdk-0.2.2.dist-info/WHEEL
cirtusai_sdk-0.2.2.dist-info/entry_points.txt
cirtusai_sdk-0.2.2.dist-info/top_level.txt
cirtusai_sdk-0.2.2.dist-info/RECORD
